os_paw/__init__.py
os_paw/api_utils.py
os_paw/products.py
os_paw/project_paths.py
os_paw/wfs_api.py
os_paw-1.0.1.dist-info/METADATA
os_paw-1.0.1.dist-info/WHEEL
os_paw-1.0.1.dist-info/license.txt
os_paw-1.0.1.dist-info/top_level.txt
os_paw-1.0.1.dist-info/RECORD
