Metadata-Version: 2.1
Name: os-paw
Version: 1.0.1
Summary: OS-PAW is the Ordnance Survey Python API Wrapper designed to make data from the OS Data Hub APIs readily accessible to python developers.
Home-page: UNKNOWN
Author: Rapid Prototyping Team
Author-email: jacob.rainbow@os.uk
License: MIT
Platform: UNKNOWN
Classifier: Programming Language :: Python :: 3
Classifier: Programming Language :: Python :: 3.8
Classifier: License :: OSI Approved :: MIT License
Requires-Dist: geojson (==2.5.0)
Requires-Dist: requests (==2.24.0)
Requires-Dist: pytest (==6.1.2)
